google/cloud/asset/__init__.py
google/cloud/asset/gapic_version.py
google/cloud/asset/py.typed
google/cloud/asset_v1/__init__.py
google/cloud/asset_v1/gapic_metadata.json
google/cloud/asset_v1/gapic_version.py
google/cloud/asset_v1/py.typed
google/cloud/asset_v1/services/__init__.py
google/cloud/asset_v1/services/asset_service/__init__.py
google/cloud/asset_v1/services/asset_service/async_client.py
google/cloud/asset_v1/services/asset_service/client.py
google/cloud/asset_v1/services/asset_service/pagers.py
google/cloud/asset_v1/services/asset_service/transports/__init__.py
google/cloud/asset_v1/services/asset_service/transports/base.py
google/cloud/asset_v1/services/asset_service/transports/grpc.py
google/cloud/asset_v1/services/asset_service/transports/grpc_asyncio.py
google/cloud/asset_v1/services/asset_service/transports/rest.py
google/cloud/asset_v1/services/asset_service/transports/rest_base.py
google/cloud/asset_v1/types/__init__.py
google/cloud/asset_v1/types/asset_enrichment_resourceowners.py
google/cloud/asset_v1/types/asset_service.py
google/cloud/asset_v1/types/assets.py
google/cloud/asset_v1p1beta1/__init__.py
google/cloud/asset_v1p1beta1/gapic_metadata.json
google/cloud/asset_v1p1beta1/gapic_version.py
google/cloud/asset_v1p1beta1/py.typed
google/cloud/asset_v1p1beta1/services/__init__.py
google/cloud/asset_v1p1beta1/services/asset_service/__init__.py
google/cloud/asset_v1p1beta1/services/asset_service/async_client.py
google/cloud/asset_v1p1beta1/services/asset_service/client.py
google/cloud/asset_v1p1beta1/services/asset_service/pagers.py
google/cloud/asset_v1p1beta1/services/asset_service/transports/__init__.py
google/cloud/asset_v1p1beta1/services/asset_service/transports/base.py
google/cloud/asset_v1p1beta1/services/asset_service/transports/grpc.py
google/cloud/asset_v1p1beta1/services/asset_service/transports/grpc_asyncio.py
google/cloud/asset_v1p1beta1/services/asset_service/transports/rest.py
google_cloud_asset-4.0.0.dist-info/licenses/LICENSE
google_cloud_asset-4.0.0.dist-info/METADATA
google_cloud_asset-4.0.0.dist-info/WHEEL
google_cloud_asset-4.0.0.dist-info/top_level.txt
google_cloud_asset-4.0.0.dist-info/RECORD
